noise_decomp/__init__.py
noise_decomp/cli.py
noise_decomp-0.1.3.dist-info/METADATA
noise_decomp-0.1.3.dist-info/WHEEL
noise_decomp-0.1.3.dist-info/entry_points.txt
noise_decomp-0.1.3.dist-info/top_level.txt
noise_decomp-0.1.3.dist-info/RECORD
