Metadata-Version: 2.4
Name: noise_decomp
Version: 0.1.3
Summary: Tiny dual-reporter intrinsic/extrinsic noise decomposition
Author-email: brchn6 <brchn6@gmail.com>
License: MIT
Classifier: Programming Language :: Python :: 3
Classifier: License :: OSI Approved :: MIT License
Classifier: Intended Audience :: Science/Research
Classifier: Topic :: Scientific/Engineering :: Bio-Informatics
Requires-Python: >=3.8
Requires-Dist: numpy>=1.20
Provides-Extra: test
Requires-Dist: pytest>=7; extra == "test"
